{
  "cnn_seed": 2028,
  "run_seed": 2028,
  "round_id": 4,
  "model_name": "mobilenetv4",
  "model_display_name": "MobileNetV4-Conv-Medium",
  "training_mode": "stylegan3",
  "epochs": 10,
  "train_loss_final": 0.062946,
  "train_accuracy_final": 0.992553,
  "elapsed_seconds": 60.85,
  "train_fold_id": 4,
  "test_fold_ids": "1,2,3,5",
  "raw_train_sample_count": 85,
  "raw_test_sample_count": 342,
  "real_train_patch_count": 821,
  "gan_train_patch_count": 119,
  "total_train_patch_count": 940,
  "test_patch_count": 3358,
  "real_train_cocci_count": 351,
  "real_train_bacilli_count": 470,
  "gan_train_cocci_count": 119,
  "gan_train_bacilli_count": 0,
  "train_cocci_count": 470,
  "train_bacilli_count": 470,
  "test_cocci_count": 1436,
  "test_bacilli_count": 1922,
  "sample_count": 3358,
  "tp": 1902,
  "tn": 1390,
  "fp": 46,
  "fn": 20,
  "accuracy": 0.980345,
  "accuracy_cocci": 0.967967,
  "accuracy_bacilli": 0.989594,
  "precision_cocci": 0.985816,
  "recall_cocci": 0.967967,
  "f1_cocci": 0.97681,
  "precision_bacilli": 0.976386,
  "recall_bacilli": 0.989594,
  "f1_bacilli": 0.982946,
  "macro_precision": 0.981101,
  "macro_recall": 0.97878,
  "macro_f1": 0.979878,
  "balanced_accuracy": 0.97878,
  "checkpoint_path": "checkpoints/57_mobilenetv4_stylegan3_dataset2/seed_2028_round_4_final.pth",
  "prediction_path": "results/57_mobilenetv4_stylegan3_dataset2/seed_2028_round_4_predictions.csv",
  "training_history_path": "results/57_mobilenetv4_stylegan3_dataset2/seed_2028_round_4_training_history.csv"
}